musicator/__init__ .py
musicator/__init__.py
musicator/tone.py
musicator-0.1.0.dist-info/METADATA
musicator-0.1.0.dist-info/WHEEL
musicator-0.1.0.dist-info/top_level.txt
musicator-0.1.0.dist-info/RECORD
