Metadata-Version: 2.1
Name: musicator
Version: 0.1.0
Summary: Music generator
Home-page: UNKNOWN
Author: Vadim Simakin
Author-email: sima.vad@yandex.com
License: UNKNOWN
Platform: UNKNOWN
Classifier: Programming Language :: Python :: 3
Classifier: Operating System :: OS Independent
Requires-Python: >=3.7
Requires-Dist: numpy
Requires-Dist: scipy
